aws_schema/__init__.py
aws_schema/__main__.py
aws_schema/_parameter_casting.py
aws_schema/_validation_base_class.py
aws_schema/api_validation.py
aws_schema/json_to_python_type.py
aws_schema/nested_dict_helper.py
aws_schema/openAPI_converter.py
aws_schema/response_validation.py
aws_schema/schema_validator.py
testing/__init__.py
testing/conftest.py
testing/test_api_validation.py
testing/test_nested_dict_helper.py
testing/test_openAPI_converting.py
testing/test_openAPI_request_validation.py
testing/test_openAPI_response_validation.py
testing/test_openAPI_selection.py
testing/test_parameter_casting.py
testing/test_response_validation.py
testing/test_schema_loading.py
testing/test_schema_validation.py
aws_schema-0.3.2.dist-info/LICENSE
aws_schema-0.3.2.dist-info/METADATA
aws_schema-0.3.2.dist-info/WHEEL
aws_schema-0.3.2.dist-info/top_level.txt
aws_schema-0.3.2.dist-info/RECORD
