Metadata-Version: 2.1
Name: aws-schema
Version: 0.3.2
Summary: simple schema verification for AWS (Serverless)
Home-page: https://github.com/janluak/aws_schema
Author: Jan Lukas Braje
Author-email: aws_schema@getkahawa.com
License: UNKNOWN
Platform: UNKNOWN
Classifier: Development Status :: 3 - Alpha
Classifier: Intended Audience :: Information Technology
Classifier: License :: OSI Approved :: Apache Software License
Classifier: Operating System :: OS Independent
Classifier: Programming Language :: Python :: 3.8
Requires-Python: >=3.8
Requires-Dist: jsonschema
Requires-Dist: pyyaml
